odoo/addons/coupon_multiplier_free_product/README.rst
odoo/addons/coupon_multiplier_free_product/__init__.py
odoo/addons/coupon_multiplier_free_product/__manifest__.py
odoo/addons/coupon_multiplier_free_product/i18n/coupon_multiplier_free_product.pot
odoo/addons/coupon_multiplier_free_product/i18n/es.po
odoo/addons/coupon_multiplier_free_product/models/__init__.py
odoo/addons/coupon_multiplier_free_product/models/coupon.py
odoo/addons/coupon_multiplier_free_product/models/coupon_program.py
odoo/addons/coupon_multiplier_free_product/models/coupon_reward.py
odoo/addons/coupon_multiplier_free_product/readme/CONFIGURE.rst
odoo/addons/coupon_multiplier_free_product/readme/CONTRIBUTORS.rst
odoo/addons/coupon_multiplier_free_product/readme/DESCRIPTION.rst
odoo/addons/coupon_multiplier_free_product/static/description/icon.png
odoo/addons/coupon_multiplier_free_product/static/description/index.html
odoo/addons/coupon_multiplier_free_product/tests/__init__.py
odoo/addons/coupon_multiplier_free_product/tests/test_coupon_multiplier_free_product.py
odoo/addons/coupon_multiplier_free_product/views/coupon_program_views.xml
odoo_addon_coupon_multiplier_free_product-15.0.1.0.0.6.dist-info/METADATA
odoo_addon_coupon_multiplier_free_product-15.0.1.0.0.6.dist-info/WHEEL
odoo_addon_coupon_multiplier_free_product-15.0.1.0.0.6.dist-info/top_level.txt
odoo_addon_coupon_multiplier_free_product-15.0.1.0.0.6.dist-info/RECORD
